apigle/__init__.py
apigle/client.py
apigle/endpoints.py
apigle/exceptions.py
apigle-1.0.3.dist-info/licenses/LICENSE
apigle-1.0.3.dist-info/METADATA
apigle-1.0.3.dist-info/WHEEL
apigle-1.0.3.dist-info/top_level.txt
apigle-1.0.3.dist-info/RECORD
