Metadata-Version: 2.4
Name: apigle
Version: 1.0.3
Summary: Official Python client for Apigle.com API
Home-page: https://github.com/boztek/apigle-python
Author: Boztek LTD
Requires-Python: >=3.7
License-File: LICENSE
Requires-Dist: requests
Dynamic: author
Dynamic: description
Dynamic: description-content-type
Dynamic: home-page
Dynamic: license-file
Dynamic: requires-dist
Dynamic: requires-python
Dynamic: summary
